clonebox/__init__.py
clonebox/__main__.py
clonebox/audit.py
clonebox/cli.py
clonebox/cloner.py
clonebox/container.py
clonebox/dashboard.py
clonebox/detector.py
clonebox/di.py
clonebox/exporter.py
clonebox/importer.py
clonebox/logging.py
clonebox/models.py
clonebox/monitor.py
clonebox/orchestrator.py
clonebox/p2p.py
clonebox/profiles.py
clonebox/resource_monitor.py
clonebox/resources.py
clonebox/rollback.py
clonebox/secrets.py
clonebox/validator.py
clonebox/backends/libvirt_backend.py
clonebox/backends/qemu_disk.py
clonebox/backends/subprocess_runner.py
clonebox/health/__init__.py
clonebox/health/manager.py
clonebox/health/models.py
clonebox/health/probes.py
clonebox/interfaces/disk.py
clonebox/interfaces/hypervisor.py
clonebox/interfaces/network.py
clonebox/interfaces/process.py
clonebox/plugins/__init__.py
clonebox/plugins/base.py
clonebox/plugins/manager.py
clonebox/snapshots/__init__.py
clonebox/snapshots/manager.py
clonebox/snapshots/models.py
clonebox/templates/profiles/ml-dev.yaml
clonebox/templates/profiles/web-stack.yaml
clonebox-1.1.14.dist-info/licenses/LICENSE
clonebox-1.1.14.dist-info/METADATA
clonebox-1.1.14.dist-info/WHEEL
clonebox-1.1.14.dist-info/entry_points.txt
clonebox-1.1.14.dist-info/top_level.txt
clonebox-1.1.14.dist-info/RECORD
