Metadata-Version: 2.4
Name: clonebox
Version: 1.1.14
Summary: Clone your workstation environment to an isolated VM with selective apps, paths and services
Author: CloneBox Team
License: Apache-2.0
Project-URL: Homepage, https://github.com/wronai/clonebox
Project-URL: Repository, https://github.com/wronai/clonebox
Project-URL: Issues, https://github.com/wronai/clonebox/issues
Keywords: vm,virtualization,libvirt,clone,workstation,qemu,kvm
Classifier: Development Status :: 4 - Beta
Classifier: Environment :: Console
Classifier: Intended Audience :: Developers
Classifier: Intended Audience :: System Administrators
Classifier: License :: OSI Approved :: Apache Software License
Classifier: Operating System :: POSIX :: Linux
Classifier: Programming Language :: Python :: 3
Classifier: Programming Language :: Python :: 3.8
Classifier: Programming Language :: Python :: 3.9
Classifier: Programming Language :: Python :: 3.10
Classifier: Programming Language :: Python :: 3.11
Classifier: Programming Language :: Python :: 3.12
Classifier: Topic :: System :: Systems Administration
Classifier: Topic :: Utilities
Requires-Python: >=3.8
License-File: LICENSE
Requires-Dist: libvirt-python>=9.0.0
Requires-Dist: rich>=13.0.0
Requires-Dist: questionary>=2.0.0
Requires-Dist: psutil>=5.9.0
Requires-Dist: pyyaml>=6.0
Requires-Dist: pydantic>=2.0.0
Requires-Dist: python-dotenv>=1.0.0
Requires-Dist: cryptography>=42.0.0
Requires-Dist: structlog>=24.0.0
Provides-Extra: dev
Requires-Dist: pytest>=7.0.0; extra == "dev"
Requires-Dist: pytest-cov>=4.0.0; extra == "dev"
Requires-Dist: black>=23.0.0; extra == "dev"
Requires-Dist: ruff>=0.1.0; extra == "dev"
Requires-Dist: mypy>=1.0.0; extra == "dev"
Provides-Extra: test
Requires-Dist: pytest>=7.0.0; extra == "test"
Requires-Dist: pytest-cov>=4.0.0; extra == "test"
Requires-Dist: pytest-timeout>=2.0.0; extra == "test"
Requires-Dist: pytest-asyncio; extra == "test"
Requires-Dist: fastapi>=0.100.0; extra == "test"
Provides-Extra: dashboard
Requires-Dist: fastapi>=0.100.0; extra == "dashboard"
Requires-Dist: uvicorn>=0.22.0; extra == "dashboard"
Dynamic: license-file
